{
  "name": "jvm_rotary_button",
  "version": "0.7",
  "displayName": "Rotary button",
  "description": "",
  "jacdac": true,
  "size": {
    "width": 27,
    "height": 16.5,
    "depth": 0
  },
  "designer": {
    "name": "Aron Eggens",
    "company": "Devices Lab"
  },
  "functionality": [
    "button",
    "rotary_encoder"
  ],
  "type": "virtual",
  "mcuPartNumber": "STM32G030F6P6",
  "publishSchematic": true,
  "designRules": {
    "canExtendToBoardEdge": false,
    "minimumClearance": null
  }
}